setup.py
fasmetrics/__init__.py
fasmetrics/fasmetrics.py
fasmetrics.egg-info/PKG-INFO
fasmetrics.egg-info/SOURCES.txt
fasmetrics.egg-info/dependency_links.txt
fasmetrics.egg-info/not-zip-safe
fasmetrics.egg-info/top_level.txt