Metadata-Version: 1.0
Name: fasmetrics
Version: 0.1
Summary: FAS metrics implementations (APCER, BPCER, ACER)
Home-page: UNKNOWN
Author: Guilherme Baldo Carlos
Author-email: guilhermebaldocarlos@gmail.com
License: UNKNOWN
Platform: UNKNOWN
